own_cli/__init__.py
own_cli/effects.py
own_cli/main.py
own_cli/transforms.py
mothilal_cli-0.1.1.dist-info/METADATA
mothilal_cli-0.1.1.dist-info/WHEEL
mothilal_cli-0.1.1.dist-info/entry_points.txt
mothilal_cli-0.1.1.dist-info/licenses/LICENSE
mothilal_cli-0.1.1.dist-info/RECORD
