Metadata-Version: 2.4
Name: mothilal-cli
Version: 0.1.1
Summary: A fun CLI that displays Mothilal's name with style, animations, and flair! ✨
Project-URL: Homepage, https://mothilal.xyz
Project-URL: Repository, https://github.com/mothilal/mothilal-cli
Author-email: Mothilal <hello@mothilal.xyz>
License-Expression: MIT
License-File: LICENSE
Keywords: animation,ascii-art,cli,mothilal,terminal
Classifier: Environment :: Console
Classifier: License :: OSI Approved :: MIT License
Classifier: Operating System :: OS Independent
Classifier: Programming Language :: Python :: 3
Classifier: Programming Language :: Python :: 3.9
Classifier: Programming Language :: Python :: 3.10
Classifier: Programming Language :: Python :: 3.11
Classifier: Programming Language :: Python :: 3.12
Requires-Python: >=3.9
Requires-Dist: pyfiglet>=1.0.0
Requires-Dist: rich>=13.0.0
Requires-Dist: typer>=0.9.0
